{
  "updatedAt": "2026-06-25T19:20:02.954Z",
  "spreadsheetId": "1dusDT6o-wpPtRTrEfELY09SwdUxSvls-3AIqQGkQMTM",
  "characters": [
    {
      "id": "1-Кафка",
      "playerName": "Максим Репин",
      "characterName": "Кафка",
      "personalFileLink": "https://vk.com/photo-36291248_457265431"
    },
    {
      "id": "2-Чжун Ли",
      "playerName": "Андрей Юриков",
      "characterName": "Чжун Ли",
      "personalFileLink": "https://vk.com/photo-36291248_457257226"
    },
    {
      "id": "3-Лара Доррен",
      "playerName": "Константин Магикян",
      "characterName": "Лара Доррен",
      "personalFileLink": "https://vk.com/photo-36291248_457265413"
    },
    {
      "id": "4-Маркус Фокс",
      "playerName": "Станислав Колмыков",
      "characterName": "Маркус Фокс",
      "personalFileLink": "https://vk.com/photo-36291248_456243830"
    },
    {
      "id": "5-Мичио Куромари",
      "playerName": "Константин Магикян",
      "characterName": "Мичио Куромари",
      "personalFileLink": "https://vk.com/photo-36291248_388469549"
    },
    {
      "id": "6-Цзинлю Хаяси",
      "playerName": "Лидия Моловствова",
      "characterName": "Цзинлю Хаяси",
      "personalFileLink": "https://vk.com/photo-36291248_457262690"
    },
    {
      "id": "7-Джек Пауль",
      "playerName": "Алишер Жакупов",
      "characterName": "Джек Пауль",
      "personalFileLink": "https://vk.com/photo-36291248_457267496"
    },
    {
      "id": "8-Изельда Уль-Бреккер",
      "playerName": "Миша Красивый",
      "characterName": "Изельда Уль-Бреккер",
      "personalFileLink": "https://vk.com/photo-36291248_457265407"
    },
    {
      "id": "9-Вильгельма Розенфельд",
      "playerName": "Илья Фролов",
      "characterName": "Вильгельма Розенфельд",
      "personalFileLink": "https://vk.com/photo-36291248_457251611"
    },
    {
      "id": "10-\"Мидгар\" Д. Зефир",
      "playerName": "Дова Кин",
      "characterName": "\"Мидгар\" Д. Зефир",
      "personalFileLink": "https://vk.com/photo-36291248_457262848"
    },
    {
      "id": "11-Тессия Д. Эралит",
      "playerName": "Remina Stirling",
      "characterName": "Тессия Д. Эралит",
      "personalFileLink": "https://vk.com/photo-36291248_457265272"
    },
    {
      "id": "12-Патрик Бенедикт Люций",
      "playerName": "Николь Грибоедов",
      "characterName": "Патрик Бенедикт Люций",
      "personalFileLink": "https://vk.com/photo-36291248_457271659"
    },
    {
      "id": "13-Юя Хитогая",
      "playerName": "Лина Камалина",
      "characterName": "Юя Хитогая",
      "personalFileLink": "https://vk.com/photo-36291248_457271966"
    },
    {
      "id": "14-Мария Икеда",
      "playerName": "Tori Tori",
      "characterName": "Мария Икеда",
      "personalFileLink": "https://vk.com/photo-36291248_457271992"
    },
    {
      "id": "15-Пипин Рейнольд Т. Майрон",
      "playerName": "Серафим Шаульский",
      "characterName": "Пипин Рейнольд Т. Майрон",
      "personalFileLink": "https://vk.com/photo-36291248_457268075"
    },
    {
      "id": "16-Нойдиллион",
      "playerName": "God Of Wine",
      "characterName": "Нойдиллион",
      "personalFileLink": "https://vk.com/photo-36291248_457272326"
    },
    {
      "id": "17-Леодеганс Гинденбург",
      "playerName": "Миокко Моккачино",
      "characterName": "Леодеганс Гинденбург",
      "personalFileLink": "https://vk.com/photo-36291248_457272403"
    },
    {
      "id": "18-Шарлотт ла Бронтье",
      "playerName": "Lisa Goethe",
      "characterName": "Шарлотт ла Бронтье",
      "personalFileLink": "https://vk.com/photo-36291248_457272436"
    }
  ]
}